imagefx/__init__.py
imagefx/main.py
tests/__init__.py
tests/tests_imagefx.py
imagefx-1.0.2.dist-info/METADATA
imagefx-1.0.2.dist-info/WHEEL
imagefx-1.0.2.dist-info/entry_points.txt
imagefx-1.0.2.dist-info/top_level.txt
imagefx-1.0.2.dist-info/RECORD
